teleping/__init__.py
teleping/common.py
teleping/config.py
teleping/templates/base.html.j2
teleping/templates/message.html.j2
teleping/templates/udpping.html.j2
teleping/udpping.py
teleping/webui.py
teleping-0.2.0.dist-info/LICENSE
teleping-0.2.0.dist-info/METADATA
teleping-0.2.0.dist-info/WHEEL
teleping-0.2.0.dist-info/entry_points.txt
teleping-0.2.0.dist-info/RECORD
